pythoncpp/compile.py
pythoncpp-0.2.dist-info/METADATA
pythoncpp-0.2.dist-info/WHEEL
pythoncpp-0.2.dist-info/entry_points.txt
pythoncpp-0.2.dist-info/RECORD
