Metadata-Version: 2.1
Name: pythoncpp
Version: 0.2
Summary: Python, compiled.
Author: dcode
Author-email: opendylan@proton.me
Requires-Python: >=3.7,<4.0
Classifier: Programming Language :: Python :: 3
Classifier: Programming Language :: Python :: 3.7
Classifier: Programming Language :: Python :: 3.8
Classifier: Programming Language :: Python :: 3.9
Classifier: Programming Language :: Python :: 3.10
Classifier: Programming Language :: Python :: 3.11
